mkdocs_vim_md_tags_plugin/__init__.py
mkdocs_vim_md_tags_plugin/plugin.py
mkdocs_vim_md_tags_plugin-0.2.0.dist-info/DESCRIPTION.rst
mkdocs_vim_md_tags_plugin-0.2.0.dist-info/METADATA
mkdocs_vim_md_tags_plugin-0.2.0.dist-info/RECORD
mkdocs_vim_md_tags_plugin-0.2.0.dist-info/WHEEL
mkdocs_vim_md_tags_plugin-0.2.0.dist-info/entry_points.txt
mkdocs_vim_md_tags_plugin-0.2.0.dist-info/metadata.json
mkdocs_vim_md_tags_plugin-0.2.0.dist-info/top_level.txt
